__init__.py
imspire_object.py
utility.py
imspire-1.2.0.data/scripts/ImSpiRE
imspire-1.2.0.dist-info/LICENSE
imspire-1.2.0.dist-info/METADATA
imspire-1.2.0.dist-info/WHEEL
imspire-1.2.0.dist-info/top_level.txt
imspire-1.2.0.dist-info/RECORD
