Metadata-Version: 2.1
Name: imspire
Version: 1.2.0
Summary: ImSpiRE is a python script (python 3.8+) for spatial resolution enhancenment by solving the entropic regularized fused Gromov-Wasserstein transport (FGW) problem for in situ capturing (ISC) spatial transcriptome.
Home-page: https://github.com/TongjiZhanglab/ImSpiRE
Author: Yuwei Hua
Author-email: ywhua@tongji.edu.com
Classifier: Development Status :: 3 - Alpha
Classifier: Intended Audience :: Developers
Classifier: Topic :: Software Development :: Build Tools
Classifier: License :: OSI Approved :: MIT License
Classifier: Programming Language :: Python :: 3.8
Requires-Python: >=3.8
License-File: LICENSE
Requires-Dist: pandas (==1.4.1)
Requires-Dist: numpy (==1.23.4)
Requires-Dist: matplotlib (==3.1.3)
Requires-Dist: scanpy (==1.9.0)
Requires-Dist: scipy (==1.9.3)
Requires-Dist: scikit-learn (==1.1.3)
Requires-Dist: numba (==0.53.0)
Requires-Dist: backgroundremover (==0.1.9)
Requires-Dist: scikit-image (==0.19.3)
Requires-Dist: anndata (==0.8.0)
Requires-Dist: tifffile
Requires-Dist: POT
Requires-Dist: opencv-python
